tracardi_event_counter/plugin.py
tracardi_event_counter/model/__init__.py
tracardi_event_counter/model/configuration.py
tracardi_event_counter/model/__pycache__/__init__.cpython-38.pyc
tracardi_event_counter/model/__pycache__/configuration.cpython-38.pyc
tracardi_event_counter/test/manual_test.py
tracardi_event_counter-0.6.0.dist-info/LICENSE.md
tracardi_event_counter-0.6.0.dist-info/METADATA
tracardi_event_counter-0.6.0.dist-info/WHEEL
tracardi_event_counter-0.6.0.dist-info/top_level.txt
tracardi_event_counter-0.6.0.dist-info/RECORD
