Metadata-Version: 2.1
Name: tracardi-event-counter
Version: 0.6.0
Summary: This plugin reads how many events of defined type were triggered within defined time.
Home-page: UNKNOWN
Author: Dawid Kruk
Author-email: krukdawid27@gmail.com
License: UNKNOWN
Keywords: tracardi,plugin
Platform: UNKNOWN
Classifier: Programming Language :: Python :: 3
Classifier: License :: OSI Approved :: MIT License
Classifier: Operating System :: OS Independent
Requires-Python: >=3.8
License-File: LICENSE.md
Requires-Dist: tracardi-plugin-sdk (>=0.6.22)
Requires-Dist: tracardi
Requires-Dist: pytimeparse
